Metadata-Version: 1.1
Name: django-mass-post-office
Version: 0.0.10
Summary: Mass Post Office
Home-page: https://github.com/42cc/mass_post_office
Author: 42coffeecups.com
Author-email: contact@42cc.co
License: UNKNOWN
Keywords: django,post-office,mass-post-office
Platform: UNKNOWN
Classifier: Programming Language :: Python
Classifier: Topic :: Software Development :: Libraries :: Python Modules
Classifier: Framework :: Django
Classifier: Environment :: Web Environment
